{"resistors":[{"polygon":[{"x":506,"y":75},{"x":704,"y":62},{"x":707,"y":141},{"x":501,"y":153}],"colors":["green","blue","red","none","gold","none"]},{"polygon":[{"x":460,"y":407},{"x":682,"y":404},{"x":684,"y":484},{"x":467,"y":484}],"colors":["green","blue","brown","none","gold","none"]},{"polygon":[{"x":75,"y":348},{"x":289,"y":349},{"x":289,"y":428},{"x":72,"y":432}],"colors":["brown","black","orange","none","gold","none"]},{"polygon":[{"x":150,"y":42},{"x":344,"y":37},{"x":349,"y":126},{"x":158,"y":125}],"colors":["brown","black","orange","none","gold","none"]}]}